gco_wrapper-3.0.9.dist-info/METADATA
gco_wrapper-3.0.9.dist-info/top_level.txt
gco_wrapper-3.0.9.dist-info/RECORD
gco_wrapper-3.0.9.dist-info/WHEEL
gco/libcgco.cpython-37m-i386-linux-gnu.so
gco/cgco.py
gco/pygco.py
gco/__about__.py
gco/cgco.h
gco/cgco.cpp
gco/__init__.py
gco_wrapper.libs/libgcc_s-8b50eaaa.so.1
gco_wrapper.libs/libstdc++-8baf04f9.so.6.0.28
