Metadata-Version: 2.1
Name: gco-wrapper
Version: 3.0.9
Summary: pyGCO: a python wrapper for the graph cuts package
Home-page: http://vision.csd.uwo.ca/code/
Download-URL: https://github.com/Borda/pyGCO
Author: Yujia Li & A. Mueller
Author-email: yujiali@cs.tornto.edu
Maintainer: Jiri Borovec
Maintainer-email: jiri.borovec@fel.cvut.cz
License: MIT
Project-URL: Source Code, https://github.com/Borda/pyGCO
Classifier: Development Status :: 4 - Beta
Classifier: Environment :: Console
Classifier: Intended Audience :: Developers
Classifier: Intended Audience :: Information Technology
Classifier: Intended Audience :: Education
Classifier: Intended Audience :: Science/Research
Classifier: License :: OSI Approved :: MIT License
Classifier: Natural Language :: English
Classifier: Programming Language :: Python :: 2
Classifier: Programming Language :: Python :: 2.7
Classifier: Programming Language :: Python :: 3
Classifier: Programming Language :: Python :: 3.6
Classifier: Programming Language :: Python :: 3.7
Classifier: Programming Language :: Python :: 3.8
Classifier: Programming Language :: Python :: 3.9
Classifier: Programming Language :: Python :: 3.10
Classifier: Programming Language :: Python :: 3.11
Requires-Dist: Cython (>=0.23.1)
Requires-Dist: numpy (>=1.8.2)
